gogs_client/__init__.py
gogs_client/auth.py
gogs_client/entities.py
gogs_client/interface.py
gogs_client/updates.py
gogs_client/_implementation/__init__.py
gogs_client/_implementation/http_utils.py
tests/__init__.py
tests/http_utils_test.py
tests/interface_test.py
tests/gogs_client/__init__.py
tests/gogs_client/auth.py
tests/gogs_client/entities.py
tests/gogs_client/interface.py
tests/gogs_client/updates.py
tests/gogs_client/_implementation/__init__.py
tests/gogs_client/_implementation/http_utils.py
gogs_client-1.0.6.dist-info/top_level.txt
gogs_client-1.0.6.dist-info/METADATA
gogs_client-1.0.6.dist-info/DESCRIPTION.rst
gogs_client-1.0.6.dist-info/metadata.json
gogs_client-1.0.6.dist-info/WHEEL
gogs_client-1.0.6.dist-info/RECORD
