Metadata-Version: 1.1
Name: gogs_client
Version: 1.0.6
Summary: A python library for interacting with a gogs server
Home-page: https://github.com/unfoldingWord-dev/python-gogs-client
Author: unfoldingWord
Author-email: ethantkoenig@gmail.com
License: MIT
Keywords: gogs,http,client
Platform: UNKNOWN
Classifier: License :: OSI Approved :: MIT License
Classifier: Programming Language :: Python :: 2.7
Classifier: Programming Language :: Python :: 3
Classifier: Programming Language :: Python :: 3.3
Classifier: Programming Language :: Python :: 3.4
Classifier: Programming Language :: Python :: 3.5
